{
    "name": "atom-sum-selected",
    "repository": {
        "type": "git",
        "url": "https://github.com/DonaldChiang/atom-sum-selected"
    },
    "downloads": 233,
    "stargazers_count": 2,
    "releases": {
        "latest": "0.1.0"
    },
    "versions": {
        "0.1.0": {
            "name": "atom-sum-selected",
            "main": "./lib/atom-sum-selected",
            "version": "0.1.0",
            "description": "Sum your selected numbers",
            "keywords": [],
            "activationCommands": {
                "atom-workspace": "atom-sum-selected:toggle"
            },
            "repository": "https://github.com/DonaldChiang/atom-sum-selected",
            "license": "MIT",
            "engines": {
                "atom": ">=1.0.0 <2.0.0"
            },
            "dependencies": {},
            "dist": {
                "tarball": "https://www.atom.io/api/packages/atom-sum-selected/versions/0.1.0/tarball"
            },
            "tarball_url": "https://api.github.com/repos/DonaldChiang/atom-sum-selected/tarball/refs/tags/v0.1.0",
            "sha": "5fb052106f48530565107ab230e73b02f5034d42"
        }
    },
    "readme": "# atom-sum-selected package\n\n![Preview](statics/atom-sum-selected.gif?raw=true \"Preview\")\n",
    "metadata": {
        "name": "atom-sum-selected",
        "main": "./lib/atom-sum-selected",
        "version": "0.1.0",
        "description": "Sum your selected numbers",
        "keywords": [],
        "activationCommands": {
            "atom-workspace": "atom-sum-selected:toggle"
        },
        "repository": "https://github.com/DonaldChiang/atom-sum-selected",
        "license": "MIT",
        "engines": {
            "atom": ">=1.0.0 <2.0.0"
        },
        "dependencies": {}
    },
    "created": 1658334196380,
    "updated": 1658334196380,
    "star_gazers": [],
    "creation_method": "Migrated from Atom.io"
}