{
    "name": "builder",
    "repository": {
        "type": "git",
        "url": "https://github.com/atom-community/builder"
    },
    "downloads": 1258,
    "stargazers_count": 4,
    "releases": {
        "latest": "0.0.1"
    },
    "versions": {
        "0.0.1": {
            "name": "builder",
            "main": "./lib/builder",
            "version": "0.0.1",
            "description": "Builds your file or project and displays the output.",
            "keywords": [
                "build",
                "builder",
                "compile"
            ],
            "repository": "https://github.com/atom-community/builder",
            "license": "MIT",
            "engines": {
                "atom": ">=1.0.0 <2.0.0"
            },
            "author": "Joe Fitzgerald <jfitzgerald@pivotal.io> (http://github.com/joefitzgerald)",
            "homepage": "https://atom.io/packages/builder",
            "bugs": {
                "url": "https://github.com/atom-community/builder/issues"
            },
            "dependencies": {},
            "devDependencies": {
                "coffeelint": ">=1.8.1",
                "temp": ">=0.8.1",
                "underscore-plus": "1.x"
            },
            "consumedServices": {
                "builder.provider": {
                    "versions": {
                        "0.1.0": "consumeProvider"
                    }
                }
            },
            "dist": {
                "tarball": "https://www.atom.io/api/packages/builder/versions/0.0.1/tarball"
            },
            "tarball_url": "https://api.github.com/repos/atom-community-archive/builder/tarball/refs/tags/v0.0.1",
            "sha": "53477a91b66eb20cc2e45358878428153a29ae98"
        }
    },
    "readme": "# builder package\n\nA short description of your package.\n\n![A screenshot of your package](https://f.cloud.github.com/assets/69169/2290250/c35d867a-a017-11e3-86be-cd7c5bf3ff9b.gif)\n",
    "metadata": {
        "name": "builder",
        "main": "./lib/builder",
        "version": "0.0.1",
        "description": "Builds your file or project and displays the output.",
        "keywords": [
            "build",
            "builder",
            "compile"
        ],
        "repository": "https://github.com/atom-community/builder",
        "license": "MIT",
        "engines": {
            "atom": ">=1.0.0 <2.0.0"
        },
        "author": "Joe Fitzgerald <jfitzgerald@pivotal.io> (http://github.com/joefitzgerald)",
        "homepage": "https://atom.io/packages/builder",
        "bugs": {
            "url": "https://github.com/atom-community/builder/issues"
        },
        "dependencies": {},
        "devDependencies": {
            "coffeelint": ">=1.8.1",
            "temp": ">=0.8.1",
            "underscore-plus": "1.x"
        },
        "consumedServices": {
            "builder.provider": {
                "versions": {
                    "0.1.0": "consumeProvider"
                }
            }
        }
    },
    "created": 1658337021551,
    "updated": 1658337021551,
    "star_gazers": [],
    "creation_method": "Migrated from Atom.io"
}