{
    "name": "seti-vs-syntax",
    "repository": {
        "type": "git",
        "url": "https://github.com/Coder911th/seti-vs-syntax"
    },
    "downloads": 13638,
    "stargazers_count": 2,
    "releases": {
        "latest": "0.1.1"
    },
    "versions": {
        "0.1.1": {
            "dependencies": {},
            "description": "This is a great syntax for seti-ui in Visual Studio style. Recommended for HTML, CSS, JS, SASS and PUG.",
            "author": "Coder911th",
            "devDependencies": {},
            "engines": {
                "atom": ">=1.0.0"
            },
            "keywords": [
                "Atom",
                "syntax",
                "theme",
                "seti",
                "vs",
                "visual",
                "studio",
                "js",
                "html",
                "css",
                "pug",
                "sass"
            ],
            "license": "MIT",
            "name": "seti-vs-syntax",
            "optionalDependencies": {},
            "repository": {
                "type": "git",
                "url": "git+https://github.com/Coder911th/seti-vs-syntax"
            },
            "theme": "syntax",
            "version": "0.1.1",
            "readmeFilename": "README.md",
            "dist": {
                "tarball": "https://www.atom.io/api/packages/seti-vs-syntax/versions/0.1.1/tarball"
            },
            "tarball_url": "https://api.github.com/repos/Coder911th/seti-vs-syntax/tarball/refs/tags/v0.1.1",
            "sha": "ce85eb380d95b4d40c5a76ebd88789f8e3277011"
        },
        "0.1.0": {
            "dependencies": {},
            "description": "This is a great syntax for seti-ui in Visual Studio style. Recommended for HTML, CSS, JS, SASS and PUG.",
            "author": "Coder911th",
            "devDependencies": {},
            "engines": {
                "atom": ">=1.0.0"
            },
            "keywords": [
                "Atom",
                "syntax",
                "theme",
                "seti",
                "vs",
                "visual",
                "studio"
            ],
            "license": "MIT",
            "name": "seti-vs-syntax",
            "optionalDependencies": {},
            "repository": {
                "type": "git",
                "url": "git+https://github.com/Coder911th/seti-vs-syntax"
            },
            "theme": "syntax",
            "version": "0.1.0",
            "readmeFilename": "README.md",
            "dist": {
                "tarball": "https://www.atom.io/api/packages/seti-vs-syntax/versions/0.1.0/tarball"
            },
            "tarball_url": "https://api.github.com/repos/Coder911th/seti-vs-syntax/tarball/refs/tags/v0.1.0",
            "sha": "49b25c9f546bf8222a7443178ec651ba2ba07d66"
        }
    },
    "readme": "# Seti Visual Studio Syntax (Atom)\n\nThis is a great syntax for [Seti-UI](https://atom.io/themes/seti-ui) in Visual Studio style.\nRecommended for HTML, CSS, JS, SASS and PUG.\n\nScreenshots\n-------------\nPUG\n![Screenshot](https://raw.githubusercontent.com/Coder911th/seti-vs-syntax/master/screenshots/pug.png \"PUG screenshot\")\nHTML\n![Screenshot](https://raw.githubusercontent.com/Coder911th/seti-vs-syntax/master/screenshots/html.png \"HTML screenshot\")\nJS\n![Screenshot](https://raw.githubusercontent.com/Coder911th/seti-vs-syntax/master/screenshots/js.png \"JS screenshot\")\n",
    "metadata": {
        "dependencies": {},
        "description": "This is a great syntax for seti-ui in Visual Studio style. Recommended for HTML, CSS, JS, SASS and PUG.",
        "author": "Coder911th",
        "devDependencies": {},
        "engines": {
            "atom": ">=1.0.0"
        },
        "keywords": [
            "Atom",
            "syntax",
            "theme",
            "seti",
            "vs",
            "visual",
            "studio",
            "js",
            "html",
            "css",
            "pug",
            "sass"
        ],
        "license": "MIT",
        "name": "seti-vs-syntax",
        "optionalDependencies": {},
        "repository": {
            "type": "git",
            "url": "git+https://github.com/Coder911th/seti-vs-syntax"
        },
        "theme": "syntax",
        "version": "0.1.1",
        "readmeFilename": "README.md"
    },
    "created": 1658426813933,
    "updated": 1658426813933,
    "star_gazers": [],
    "creation_method": "Migrated from Atom.io"
}