{
  "name": "linearize",
  "repository": {
    "type": "git",
    "url": "https://github.com/raworre/linearize"
  },
  "downloads": 413,
  "stargazers_count": 0,
  "releases": {
    "latest": "0.1.1"
  },
  "versions": {
    "0.1.1": {
      "name": "linearize",
      "main": "./lib/linearize",
      "version": "0.1.1",
      "description": "Removes line breaks from the text editor to create a single line.",
      "keywords": [],
      "activationCommands": {
        "atom-workspace": "linearize:convert"
      },
      "repository": "https://github.com/raworre/linearize",
      "license": "MIT",
      "engines": {
        "atom": ">=1.0.0 <2.0.0"
      },
      "dependencies": {},
      "bugs": {
        "url": "https://github.com/raworre/linearize/issues"
      },
      "dist": {
        "tarball": "https://www.atom.io/api/packages/linearize/versions/0.1.1/tarball"
      }
    },
    "0.1.0": {
      "name": "linearize",
      "main": "./lib/linearize",
      "version": "0.1.0",
      "description": "A short description of your package",
      "keywords": [],
      "activationCommands": {
        "atom-workspace": "linearize:convert"
      },
      "repository": "https://github.com/raworre/linearize",
      "license": "MIT",
      "engines": {
        "atom": ">=1.0.0 <2.0.0"
      },
      "dependencies": {},
      "bugs": {
        "url": "https://github.com/raworre/linearize/issues"
      },
      "dist": {
        "tarball": "https://www.atom.io/api/packages/linearize/versions/0.1.0/tarball"
      }
    }
  },
  "readme": "# linearize package\n\nLinearizes the text editor with a single keypress (Default Ctrl+Alt+l)\n\nGreat if you need to put XML, HTML, or XHTML into a single line.\n\nJSON partial support included.\n\n![A screenshot of your package](https://f.cloud.github.com/assets/69169/2290250/c35d867a-a017-11e3-86be-cd7c5bf3ff9b.gif)\n",
  "metadata": {
    "name": "linearize",
    "main": "./lib/linearize",
    "version": "0.1.1",
    "description": "Removes line breaks from the text editor to create a single line.",
    "keywords": [],
    "activationCommands": {
      "atom-workspace": "linearize:convert"
    },
    "repository": "https://github.com/raworre/linearize",
    "license": "MIT",
    "engines": {
      "atom": ">=1.0.0 <2.0.0"
    },
    "dependencies": {},
    "bugs": {
      "url": "https://github.com/raworre/linearize/issues"
    }
  }
}