{
  "name": "markdown-toolbar",
  "repository": {
    "type": "git",
    "url": "https://github.com/josex2r/markdown-toolbar"
  },
  "downloads": 3744,
  "stargazers_count": 13,
  "releases": {
    "latest": "0.1.2"
  },
  "versions": {
    "0.1.2": {
      "name": "markdown-toolbar",
      "main": "./lib/markdown-toolbar",
      "version": "0.1.2",
      "description": "Small markdown toolbar to make easy add context to your files",
      "keywords": [],
      "repository": "https://github.com/josex2r/markdown-toolbar",
      "license": "MIT",
      "engines": {
        "atom": ">=1.0.0 <2.0.0"
      },
      "dependencies": {},
      "dist": {
        "tarball": "https://www.atom.io/api/packages/markdown-toolbar/versions/0.1.2/tarball"
      }
    },
    "0.1.1": {
      "name": "markdown-toolbar",
      "main": "./lib/markdown-toolbar",
      "version": "0.1.1",
      "description": "Small markdown toolbar to make easy add context to your files",
      "keywords": [],
      "repository": "https://github.com/josex2r/markdown-toolbar",
      "license": "MIT",
      "engines": {
        "atom": ">=1.0.0 <2.0.0"
      },
      "dependencies": {},
      "dist": {
        "tarball": "https://www.atom.io/api/packages/markdown-toolbar/versions/0.1.1/tarball"
      }
    },
    "0.1.0": {
      "name": "markdown-toolbar",
      "main": "./lib/markdown-toolbar",
      "version": "0.1.0",
      "description": "Small markdown toolbar to make easy add context to your files",
      "keywords": [],
      "repository": "https://github.com/josex2r/markdown-toolbar",
      "license": "MIT",
      "engines": {
        "atom": ">=1.0.0 <2.0.0"
      },
      "dependencies": {},
      "dist": {
        "tarball": "https://www.atom.io/api/packages/markdown-toolbar/versions/0.1.0/tarball"
      }
    }
  },
  "readme": "# markdown-toolbar\n\n[![Plugin installs!](https://img.shields.io/apm/dm/markdown-toolbar.svg?style=flat-square)](https://atom.io/packages/markdown-toolbar)\n[![Package version!](https://img.shields.io/apm/v/markdown-toolbar.svg?style=flat-square)](https://atom.io/packages/markdown-toolbar)\n[![Dependencies!](https://img.shields.io/david/josex2r/markdown-toolbar.svg?style=flat-square)](https://david-dm.org/josex2r/markdown-toolbar)\n\nSmall markdown toolbar to make easy add context to your files.\n\nInspired in [Github's toolbar](https://github.com/blog/2097-improved-commenting-with-markdown).\n\n![markdown-toolbar](https://raw.githubusercontent.com/josex2r/markdown-toolbar/master/markdown-toolbar.png)\n\n#### How to / Installation\n\nInstall package through Atom or use CLI:\n\n```\n$ apm install markdown-toolbar\n```\n\n#### License\n\nmarkdown-toolbar is released under the [MIT License](http://opensource.org/licenses/MIT).\n",
  "metadata": {
    "name": "markdown-toolbar",
    "main": "./lib/markdown-toolbar",
    "version": "0.1.2",
    "description": "Small markdown toolbar to make easy add context to your files",
    "keywords": [],
    "repository": "https://github.com/josex2r/markdown-toolbar",
    "license": "MIT",
    "engines": {
      "atom": ">=1.0.0 <2.0.0"
    },
    "dependencies": {}
  }
}