{
  "name": "polychrome-ui-breezydark",
  "repository": {
    "type": "git",
    "url": "https://github.com/alphachung/polychrome-ui-breezydark"
  },
  "downloads": 798,
  "stargazers_count": 1,
  "releases": {
    "latest": "0.3.1"
  },
  "versions": {
    "0.3.1": {
      "name": "polychrome-ui-breezydark",
      "theme": "ui",
      "version": "0.3.1",
      "description": "Modified Polychrome UI theme to fit in better with the Breeze Dark color scheme of KDE 5",
      "repository": "https://github.com/alphachung/polychrome-ui-breezydark",
      "license": "MIT",
      "engines": {
        "atom": ">0.50.0"
      },
      "dependencies": {},
      "dist": {
        "tarball": "https://www.atom.io/api/packages/polychrome-ui-breezydark/versions/0.3.1/tarball"
      }
    },
    "0.3.0": {
      "name": "polychrome-ui-breezydark",
      "theme": "ui",
      "version": "0.3.0",
      "description": "Modified Polychrome UI theme to fit in better with the Breeze Dark color scheme of KDE 5",
      "repository": "https://github.com/alphachung/polychrome-ui-breezydark",
      "license": "MIT",
      "engines": {
        "atom": ">0.50.0"
      },
      "dependencies": {},
      "dist": {
        "tarball": "https://www.atom.io/api/packages/polychrome-ui-breezydark/versions/0.3.0/tarball"
      }
    }
  },
  "readme": "# Polychrome UI Breezy Theme\n\nThe Polychrome UI theme, modified to fit in better with the Breeze Dark colors of the KDE Framework 5 / Plasma 5 Desktop. (It is not exactly those colors, but the color temperature fits in better)\n\n![polychrome](http://i.imgur.com/CH8fzkz.png)\n",
  "metadata": {
    "name": "polychrome-ui-breezydark",
    "theme": "ui",
    "version": "0.3.1",
    "description": "Modified Polychrome UI theme to fit in better with the Breeze Dark color scheme of KDE 5",
    "repository": "https://github.com/alphachung/polychrome-ui-breezydark",
    "license": "MIT",
    "engines": {
      "atom": ">0.50.0"
    },
    "dependencies": {}
  }
}